<?xml version="1.0" encoding="utf-8"?>
<odoo>

<!--        <record id="view_ddt_create_invoice_services" model="ir.ui.view">-->
<!--            <field name="name">DdT Create Invoice Services</field>-->
<!--            <field name="model">ddt.create.invoice</field>-->
<!--            <field name="inherit_id" ref="l10n_it_ddt.view_ddt_create_invoice"/>-->
<!--            <field name="arch" type="xml">-->
<!--                <field name="ddt_ids" position="after">-->
<!--                    <group>-->
<!--                        <field name="invoice_services"/>-->
<!--                        <field name="service_ids"-->
<!--                               attrs="{'invisible':[('invoice_services','!=', True)]}">-->
<!--                            <tree>-->
<!--                                <field name="order_id"/>-->
<!--                                <field name="product_id"/>-->
<!--                                <field name="name"/>-->
<!--                                <field name="qty_to_invoice"/>-->
<!--                            </tree>-->
<!--                        </field>-->
<!--                    </group>-->
<!--                </field>-->
<!--            </field>-->
<!--        </record>-->

</odoo>
